[{"status":"true",
  "referer":"https://stage.payment.schibsted.no/auth/login",
  "clientId":"[Your client ID]",
  "trackingRef":false,
  "userId":[0, 0, 1, 0, 0, 1],
  "userAgent":
  "Mozilla/5.0 (Macintosh; Intel Mac OS X 10_9_1) AppleWebKit/537.36 (KHTML, like Gecko) Chrome/33.0.1750.146 Safari/537.36",
  "hash":"eae6bc4667f6a311b3563072f2962b36",
  "trackingTag":false,
  "merchantId":"[Your merchant ID]",
  "created":"2014-03-13 12:15:22",
  "email":"user@domain.tld",
  "type":"normal",
  "initialReferer":"https://stage.payment.schibsted.no/auth/login",
  "provider":"default",
  "id":"150008804",
  "ip":"127.0.0.1"}]
